dace_query/__init__.py
dace_query/__version__.py
dace_query/config.ini
dace_query/dace.py
dace_query/astrometry/__init__.py
dace_query/astrometry/astrometry.py
dace_query/atmosphericSpectroscopy/__init__.py
dace_query/atmosphericSpectroscopy/atmosphericSpectroscopy.py
dace_query/catalog/__init__.py
dace_query/catalog/catalog.py
dace_query/cheops/__init__.py
dace_query/cheops/cheops.py
dace_query/exoplanet/__init__.py
dace_query/exoplanet/exoplanet.py
dace_query/imaging/__init__.py
dace_query/imaging/imaging.py
dace_query/lossy/__init__.py
dace_query/lossy/lossy.py
dace_query/monitoring/__init__.py
dace_query/monitoring/monitoring.py
dace_query/opacity/__init__.py
dace_query/opacity/atom.py
dace_query/opacity/molecule.py
dace_query/opendata/__init__.py
dace_query/opendata/opendata.py
dace_query/photometry/__init__.py
dace_query/photometry/photometry.py
dace_query/population/__init__.py
dace_query/population/population.py
dace_query/spectroscopy/__init__.py
dace_query/spectroscopy/spectroscopy.py
dace_query/sun/__init__.py
dace_query/sun/sun.py
dace_query/target/__init__.py
dace_query/target/target.py
dace_query/tess/__init__.py
dace_query/tess/tess.py
dace_query-2.0.0.dist-info/LICENSE
dace_query-2.0.0.dist-info/METADATA
dace_query-2.0.0.dist-info/WHEEL
dace_query-2.0.0.dist-info/top_level.txt
dace_query-2.0.0.dist-info/RECORD
