Metadata-Version: 2.2
Name: dace-query
Version: 2.0.0
Summary: dace-query allows for easy querying of DACE and provides access to both public and private data through a simple utility.
Author-email: dace-team <dace-support@unige.ch>
Maintainer-email: dace-team <dace-support@unige.ch>
License:                     GNU GENERAL PUBLIC LICENSE
Project-URL: Homepage, https://dace.unige.ch/
Project-URL: Repository, https://github.com/astro-dace/dace-query
Project-URL: Issues, https://github.com/astro-dace/dace-query/issues
Project-URL: Documentation, https://dace-query.readthedocs.io/en/latest/
Classifier: Programming Language :: Python :: 3
Classifier: Operating System :: OS Independent
Classifier: License :: OSI Approved :: GNU General Public License v3 (GPLv3)
Requires-Python: >=3.8
License-File: LICENSE
Requires-Dist: astropy>=5.1.1
Requires-Dist: astroquery>=0.4.10
Requires-Dist: numpy>=1.23.4
Requires-Dist: pandas>=2.0.0
Requires-Dist: requests>=2.32.3
